dbt_fusion_package_tools-0.18.7.dist-info/METADATA
dbt_fusion_package_tools-0.18.7.dist-info/WHEEL
dbt_fusion_package_tools-0.18.7.dist-info/entry_points.txt
dbt_fusion_package_tools/__init__.py
dbt_fusion_package_tools/check_parse_conformance.py
dbt_fusion_package_tools/compatibility.py
dbt_fusion_package_tools/dbt_package.py
dbt_fusion_package_tools/dbt_package_version.py
dbt_fusion_package_tools/exceptions.py
dbt_fusion_package_tools/fusion_version_compatibility_output.py
dbt_fusion_package_tools/manual_overrides.py
dbt_fusion_package_tools/package_example.py
dbt_fusion_package_tools/scripts/__init__.py
dbt_fusion_package_tools/scripts/conformance_output.py
dbt_fusion_package_tools/scripts/get_fusion_compatible_versions.py
dbt_fusion_package_tools/scripts/get_package_hub_files.py
dbt_fusion_package_tools/scripts/package_hub_fusion_compatibility.py
dbt_fusion_package_tools/scripts/packages_with_fusion_compatibility_changes.py
dbt_fusion_package_tools/scripts/update_package_hub_json.py
dbt_fusion_package_tools/upgrade_status.py
dbt_fusion_package_tools/version_utils.py
dbt_fusion_package_tools/yaml/__init__.py
dbt_fusion_package_tools/yaml/loader.py
dbt_fusion_package_tools-0.18.7.dist-info/RECORD
