Metadata-Version: 2.1
Name: dbt-fusion-package-tools
Version: 0.18.7
Summary: Add your description here
Requires-Python: <3.14,>=3.10
Requires-Dist: mashumaro<3.15,>=3.9
Requires-Dist: pyyaml>=6.0.2; python_version >= "3.13"
Requires-Dist: pyyaml>=6.0; python_version < "3.13"
Requires-Dist: dbt-protos>=1.0.410
Requires-Dist: requests<3.0.0
Requires-Dist: rich>=14.0.0
Requires-Dist: click<9.0,>=8.2.0
Requires-Dist: typer>=0.16.0
